MANIFEST.in
README.md
setup.py
apiview_doc/__init__.py
apiview_doc/admin.py
apiview_doc/apps.py
apiview_doc/decorator.py
apiview_doc/models.py
apiview_doc/openapi.py
apiview_doc/settings.py
apiview_doc/tests.py
apiview_doc/views.py
apiview_doc/static/apiview_doc/docs/layui/layui.js
apiview_doc/static/apiview_doc/docs/layui/css/layui.css
apiview_doc/static/apiview_doc/docs/layui/css/modules/code.css
apiview_doc/static/apiview_doc/docs/layui/css/modules/laydate/default/laydate.css
apiview_doc/static/apiview_doc/docs/layui/css/modules/layer/default/icon-ext.png
apiview_doc/static/apiview_doc/docs/layui/css/modules/layer/default/icon.png
apiview_doc/static/apiview_doc/docs/layui/css/modules/layer/default/layer.css
apiview_doc/static/apiview_doc/docs/layui/font/iconfont.eot
apiview_doc/static/apiview_doc/docs/layui/font/iconfont.svg
apiview_doc/static/apiview_doc/docs/layui/font/iconfont.ttf
apiview_doc/static/apiview_doc/docs/layui/font/iconfont.woff
apiview_doc/static/apiview_doc/docs/layui/font/iconfont.woff2
apiview_doc/static/apiview_doc/openapi/css/index.css
apiview_doc/static/apiview_doc/openapi/js/vue.min.js
apiview_doc/templates/apiview_doc/docs/content.html
apiview_doc/templates/apiview_doc/docs/index.html
apiview_doc/templates/apiview_doc/docs/sidebar.html
apiview_doc/templates/apiview_doc/openapi/aside_menu.html
apiview_doc/templates/apiview_doc/openapi/content.html
apiview_doc/templates/apiview_doc/openapi/index.html
apiview_doc/templatetags/__init__.py
apiview_doc/templatetags/pioneertags.py
djangoapiviewdoc.egg-info/PKG-INFO
djangoapiviewdoc.egg-info/SOURCES.txt
djangoapiviewdoc.egg-info/dependency_links.txt
djangoapiviewdoc.egg-info/requires.txt
djangoapiviewdoc.egg-info/top_level.txt