Metadata-Version: 2.1
Name: djangoapiviewdoc
Version: 1.1.3
Summary: Django APIView decorator create Api Doc
Home-page: https://gitee.com/zhsjch/djangoapiviewdoc.git
Author: JiChao Song
Author-email: jichaosong@outlook.com
License: BSD
Platform: UNKNOWN
Requires-Python: >=3.6
